{"ret":"0","msg":"","couponList":[{"id":"1","desc":"买任意套餐加3.5元得蜜桃派一个。","sellerId":"56","img":"http://www.mcdonalds.com.cn/images/mclub/coupon_100714/coupon_all_100714_27.jpg","sellerName":"麦当劳"},{"id":"2","desc":"麦辣鸡翅（两块）+可口可乐，10元，省3.5元，本券每日上午10点以后使用。","sellerId":"56","img":"http://kfc.img.xixik.net/c/mdl/5953ab389c9c41a0.jpg","sellerName":"麦当劳"},{"id":"3","desc":"麦辣鸡翅（两块）+小薯条，11元，本券每日上午10点以后使用。","sellerId":"56","img":"http://www.mcdonalds.com.cn/images/mclub/coupon_111212/coupon_111212_27.jpg","sellerName":"麦当劳"},{"id":"4","desc":"麦辣鸡翅（4块）+麦乐鸡（5块）+可口可乐（2杯），24元，立省6元。","sellerId":"56","img":"http://kfc.img.xixik.net/c/mdl/6e6e275bf6251bfb.jpg","sellerName":"麦当劳"},{"id":"5","desc":"巨无霸+雀巢冰爽茶，14.5元。","sellerId":"56","img":"http://kfc.img.xixik.net/c/mdl/6e6e275bf6251bfb.jpg","sellerName":"麦当劳"},{"id":"6","desc":"麦炫酷（阳光橙口味）+薯条（中），12.5元。","sellerId":"56","img":"http://kfc.img.xixik.net/c/mdl/xixik_mdl_2232233a44cfea96.jpg","sellerName":"麦当劳"}]}